aiomeshtastic/__init__.py
aiomeshtastic/bt_connection.py
aiomeshtastic/bt_logs.py
aiomeshtastic/client.py
aiomeshtastic/py.typed
aiomeshtastic/serial_connection.py
aiomeshtastic/stream_connection.py
aiomeshtastic/tcp_connection.py
meshtastic/admin_pb2.py
meshtastic/admin_pb2.pyi
meshtastic/apponly_pb2.py
meshtastic/apponly_pb2.pyi
meshtastic/atak_pb2.py
meshtastic/atak_pb2.pyi
meshtastic/cannedmessages_pb2.py
meshtastic/cannedmessages_pb2.pyi
meshtastic/channel_pb2.py
meshtastic/channel_pb2.pyi
meshtastic/clientonly_pb2.py
meshtastic/clientonly_pb2.pyi
meshtastic/config_pb2.py
meshtastic/config_pb2.pyi
meshtastic/connection_status_pb2.py
meshtastic/connection_status_pb2.pyi
meshtastic/localonly_pb2.py
meshtastic/localonly_pb2.pyi
meshtastic/mesh_pb2.py
meshtastic/mesh_pb2.pyi
meshtastic/module_config_pb2.py
meshtastic/module_config_pb2.pyi
meshtastic/mqtt_pb2.py
meshtastic/mqtt_pb2.pyi
meshtastic/paxcount_pb2.py
meshtastic/paxcount_pb2.pyi
meshtastic/portnums_pb2.py
meshtastic/portnums_pb2.pyi
meshtastic/remote_hardware_pb2.py
meshtastic/remote_hardware_pb2.pyi
meshtastic/rtttl_pb2.py
meshtastic/rtttl_pb2.pyi
meshtastic/storeforward_pb2.py
meshtastic/storeforward_pb2.pyi
meshtastic/telemetry_pb2.py
meshtastic/telemetry_pb2.pyi
meshtastic/xmodem_pb2.py
meshtastic/xmodem_pb2.pyi
aiomeshtastic-6.dist-info/LICENSE
aiomeshtastic-6.dist-info/METADATA
aiomeshtastic-6.dist-info/WHEEL
aiomeshtastic-6.dist-info/top_level.txt
aiomeshtastic-6.dist-info/RECORD
