Metadata-Version: 2.1
Name: aiomeshtastic
Version: 6
Summary: asyncio bindings to the meshtastic device API.
Author-email: Jason Michalski <armooo@armooo.net>
Requires-Python: >=3.7
License-File: LICENSE
Requires-Dist: protobuf
Requires-Dist: pyserial-asyncio
Requires-Dist: bleak
